[
  {
    "prNumber": 28,
    "branchName": "codex/make-preview-button-redirect-to-staging",
    "title": "Always route Preview / Staging badge to staging root",
    "label": "codex/make-preview-button-redirect-to-staging · PR #28",
    "previewPathSegment": "pr-28",
    "url": "/staging/pr-28/",
    "updatedAt": "2026-04-03T20:36:19.805Z"
  },
  {
    "prNumber": 27,
    "branchName": "codex/update-mulesoft,-java,-and-steam-icons",
    "title": "Update Steam/Java/MuleSoft icons and show trademark disclaimers in skill dialog",
    "label": "codex/update-mulesoft,-java,-and-steam-icons · PR #27",
    "previewPathSegment": "pr-27",
    "url": "/staging/pr-27/",
    "updatedAt": "2026-04-03T20:36:10.559Z"
  }
]
